<?xml version="1.0"?>
<PropertyList>
<generic>
   <output>
      <line_separator>newline</line_separator>
      <var_separator>tab</var_separator>
      <chunk>
         <name>/fdm/jsbsim/attitude/phi-deg</name>
         <node>/fdm/jsbsim/attitude/phi-deg</node>
         <type>float</type>
         <format>%f</format>
      </chunk>
      <chunk>
         <name>/fdm/jbsim/attitude/theta-deg</name>
         <node>/fdm/jbsim/attitude/theta-deg</node>
         <type>float</type>
         <format>%f</format>
      </chunk>
      <chunk>
         <name>/fdm/jbsim/attitude/psi-deg</name>
         <node>/fdm/jbsim/attitude/psi-deg</node>
         <type>float</type>
         <format>%f</format>
      </chunk>
      <chunk>
         <name>/orientation/roll-rate-degps</name>
         <node>/orientation/roll-rate-degps</node>
         <type>float</type>
         <format>%f</format>
      </chunk>
      <chunk>
         <name>/orientation/pitch-rate-degps</name>
         <node>/orientation/pitch-rate-degps</node>
         <type>float</type>
         <format>%f</format>
      </chunk>
      <chunk>
         <name>/orientation/yaw-rate-degps</name>
         <node>/orientation/yaw-rate-degps</node>
         <type>float</type>
         <format>%f</format>
      </chunk>
      <chunk>
         <name>/accelerations/pilot/x-accel-fps_sec</name>
         <node>/accelerations/pilot/x-accel-fps_sec</node>
         <type>float</type>
         <format>%f</format>
      </chunk>
      <chunk>
         <name>/accelerations/pilot/y-accel-fps_sec</name>
         <node>/accelerations/pilot/y-accel-fps_sec</node>
         <type>float</type>
         <format>%f</format>
      </chunk>
      <chunk>
         <name>/accelerations/pilot/z-accel-fps_sec</name>
         <node>/accelerations/pilot/z-accel-fps_sec</node>
         <type>float</type>
         <format>%f</format>
      </chunk>
      <chunk>
         <name>/instrumentation/altimeter/indicated-altitude-ft</name>
         <node>/accelerations/pilot/z-accel-fps_sec</node>
         <type>float</type>
         <format>%f</format>
      </chunk>
   </output>
</generic>
</PropertyList>
